{
  "updated_at": "2026-06-19T15:42:57.765106+00:00",
  "total": 2,
  "items": [
    {
      "tribunal": "STF",
      "title": "Confira os destaques do Plenário Virtual",
      "summary": "Sessão virtual começou às 11h desta sexta-feira (19) e termina no dia 26/06, às 23h59",
      "url": "https://noticias.stf.jus.br/postsnoticias/confira-os-destaques-do-plenario-virtual-21/",
      "date": "2026-06-19",
      "category": "Constitucional"
    },
    {
      "tribunal": "STF",
      "title": "STF 135 anos: decisão histórica da Corte garantiu reconhecimento das uniões homoafetivas",
      "summary": "Série “Tá na Nossa História” revisita primórdios da Corte, marcos institucionais, evolução de competências e seu papel na consolidação da República, da democracia e dos direitos fundamentais",
      "url": "https://noticias.stf.jus.br/postsnoticias/stf-135-anos-decisao-historica-da-corte-garantiu-reconhecimento-das-unioes-homoafetivas/",
      "date": "2026-06-19",
      "category": "Constitucional"
    }
  ]
}